commerce_shopper_search/__init__.py
commerce_shopper_search/_base_client.py
commerce_shopper_search/_client.py
commerce_shopper_search/_compat.py
commerce_shopper_search/_constants.py
commerce_shopper_search/_exceptions.py
commerce_shopper_search/_files.py
commerce_shopper_search/_models.py
commerce_shopper_search/_qs.py
commerce_shopper_search/_resource.py
commerce_shopper_search/_response.py
commerce_shopper_search/_streaming.py
commerce_shopper_search/_types.py
commerce_shopper_search/_version.py
commerce_shopper_search/py.typed
commerce_shopper_search/_utils/__init__.py
commerce_shopper_search/_utils/_compat.py
commerce_shopper_search/_utils/_datetime_parse.py
commerce_shopper_search/_utils/_logs.py
commerce_shopper_search/_utils/_proxy.py
commerce_shopper_search/_utils/_reflection.py
commerce_shopper_search/_utils/_resources_proxy.py
commerce_shopper_search/_utils/_streams.py
commerce_shopper_search/_utils/_sync.py
commerce_shopper_search/_utils/_transform.py
commerce_shopper_search/_utils/_typing.py
commerce_shopper_search/_utils/_utils.py
commerce_shopper_search/lib/.keep
commerce_shopper_search/resources/__init__.py
commerce_shopper_search/resources/organizations.py
commerce_shopper_search/types/__init__.py
commerce_shopper_search/types/currency_code.py
commerce_shopper_search/types/currency_code_param.py
commerce_shopper_search/types/image.py
commerce_shopper_search/types/organization_product_search_params.py
commerce_shopper_search/types/organization_product_search_response.py
commerce_shopper_search/types/organization_search_suggestions_params.py
commerce_shopper_search/types/organization_search_suggestions_response.py
commerce_shopper_search/types/product_price_table.py
commerce_shopper_search/types/product_promotion.py
commerce_shopper_search/types/product_ref.py
commerce_shopper_search/types/product_search_refinement_value.py
commerce_shopper_search/types/suggested_phrase.py
commerce_shopper_search/types/suggested_terms.py
commerce_shopper_search-0.1.0.dist-info/METADATA
commerce_shopper_search-0.1.0.dist-info/WHEEL
commerce_shopper_search-0.1.0.dist-info/licenses/LICENSE
commerce_shopper_search-0.1.0.dist-info/RECORD
